dredis/__init__.py
dredis/commands.py
dredis/config.py
dredis/crc64.py
dredis/db.py
dredis/exceptions.py
dredis/gc.py
dredis/keyspace.py
dredis/lua.py
dredis/parser.py
dredis/path.py
dredis/rdb.py
dredis/server.py
dredis/utils.py
dredis/contrib/__init__.py
dredis/contrib/convert_key_format_to_2_5_3.py
dredis/contrib/snapshot_lmdb.py
dredis-2.6.0.dist-info/LICENSE
dredis-2.6.0.dist-info/METADATA
dredis-2.6.0.dist-info/WHEEL
dredis-2.6.0.dist-info/entry_points.txt
dredis-2.6.0.dist-info/top_level.txt
dredis-2.6.0.dist-info/RECORD
