Metadata-Version: 2.1
Name: dredis
Version: 2.6.0
Summary: Disk-based Redis implementation
Home-page: https://github.com/Yipit/dredis
Author: Yipit Coders
Author-email: coders@yipitdata.com
License: UNKNOWN
Platform: UNKNOWN
Classifier: Programming Language :: Python
Classifier: License :: OSI Approved :: MIT License
Classifier: Topic :: Database
Requires-Dist: lupa
Requires-Dist: six
Requires-Dist: plyvel
Requires-Dist: lmdb
Requires-Dist: python-lzf
